odoo/addons/stock_inventory_count_to_zero/README.rst
odoo/addons/stock_inventory_count_to_zero/__init__.py
odoo/addons/stock_inventory_count_to_zero/__manifest__.py
odoo/addons/stock_inventory_count_to_zero/i18n/es.po
odoo/addons/stock_inventory_count_to_zero/i18n/fr.po
odoo/addons/stock_inventory_count_to_zero/i18n/it.po
odoo/addons/stock_inventory_count_to_zero/i18n/stock_inventory_count_to_zero.pot
odoo/addons/stock_inventory_count_to_zero/i18n/stock_request_count_to_zero.pot
odoo/addons/stock_inventory_count_to_zero/models/__init__.py
odoo/addons/stock_inventory_count_to_zero/models/stock_quant.py
odoo/addons/stock_inventory_count_to_zero/readme/CONTRIBUTORS.md
odoo/addons/stock_inventory_count_to_zero/readme/DESCRIPTION.md
odoo/addons/stock_inventory_count_to_zero/readme/USAGE.md
odoo/addons/stock_inventory_count_to_zero/static/description/icon.png
odoo/addons/stock_inventory_count_to_zero/static/description/index.html
odoo/addons/stock_inventory_count_to_zero/tests/__init__.py
odoo/addons/stock_inventory_count_to_zero/tests/test_stock_inventory_count_to_zero.py
odoo/addons/stock_inventory_count_to_zero/wizards/__init__.py
odoo/addons/stock_inventory_count_to_zero/wizards/stock_request_count.py
odoo_addon_stock_inventory_count_to_zero-18.0.1.0.0.2.dist-info/METADATA
odoo_addon_stock_inventory_count_to_zero-18.0.1.0.0.2.dist-info/WHEEL
odoo_addon_stock_inventory_count_to_zero-18.0.1.0.0.2.dist-info/top_level.txt
odoo_addon_stock_inventory_count_to_zero-18.0.1.0.0.2.dist-info/RECORD
